bdrk/__init__.py
bdrk/backend/__init__.py
bdrk/backend/utils/__init__.py
bdrk/backend/utils/v1.py
bdrk/backend/v1/__init__.py
bdrk/backend/v1/api_client.py
bdrk/backend/v1/configuration.py
bdrk/backend/v1/exceptions.py
bdrk/backend/v1/rest.py
bdrk/backend/v1/api/__init__.py
bdrk/backend/v1/api/internal_api.py
bdrk/backend/v1/api/model_api.py
bdrk/backend/v1/api/pipeline_api.py
bdrk/backend/v1/api/project_api.py
bdrk/backend/v1/api/serve_api.py
bdrk/backend/v1/models/__init__.py
bdrk/backend/v1/models/add_upstream_model_request_schema.py
bdrk/backend/v1/models/artefact_download_url_schema.py
bdrk/backend/v1/models/artefact_upload_url_schema.py
bdrk/backend/v1/models/blob_storage_signed_url_schema.py
bdrk/backend/v1/models/create_model_artefact_schema.py
bdrk/backend/v1/models/git_source_schema.py
bdrk/backend/v1/models/metric_point_schema.py
bdrk/backend/v1/models/model_artefact_collection_schema.py
bdrk/backend/v1/models/model_artefact_schema.py
bdrk/backend/v1/models/model_endpoint_schema.py
bdrk/backend/v1/models/model_server_schema.py
bdrk/backend/v1/models/pipeline_resources_schema.py
bdrk/backend/v1/models/pipeline_run_parameters_schema.py
bdrk/backend/v1/models/project_schema.py
bdrk/backend/v1/models/run_metric_schema.py
bdrk/backend/v1/models/server_resources_schema.py
bdrk/backend/v1/models/start_training_run_schema.py
bdrk/backend/v1/models/training_pipeline_run_schema.py
bdrk/backend/v1/models/training_pipeline_schema.py
bdrk/backend/v1/models/training_run_and_steps_schema.py
bdrk/backend/v1/models/training_run_step_schema.py
bdrk/backend/v1/models/update_pipeline_run_metric_schema.py
bdrk/backend/v1/models/update_pipeline_run_status_schema.py
bdrk/backend/v1/models/user_schema.py
bdrk/backend/v1/models/xafai_download_url_schema.py
bdrk/backend/v1/models/xafai_upload_url_schema.py
bdrk/model/__init__.py
bdrk/model/base.py
bdrk/model_analyzer/__init__.py
bdrk/model_analyzer/classifier_fairness.py
bdrk/model_analyzer/explainability.py
bdrk-0.9.2.dist-info/METADATA
bdrk-0.9.2.dist-info/WHEEL
bdrk-0.9.2.dist-info/entry_points.txt
bdrk-0.9.2.dist-info/top_level.txt
bdrk-0.9.2.dist-info/RECORD
