Metadata-Version: 2.1
Name: bdrk
Version: 0.9.2
Summary: Client library for Bedrock platform
Home-page: https://github.com/basisai/span
Author: basis-ai.com
Author-email: contact@basis-ai.com
License: UNKNOWN
Platform: UNKNOWN
Classifier: Programming Language :: Python :: 3
Requires-Dist: requests (<3.0,>=2.2)
Requires-Dist: six (<2.0,>=1.14.0)
Provides-Extra: analyzer
Requires-Dist: aif360 (==0.3.0) ; extra == 'analyzer'
Requires-Dist: boxkite (<0.1,>=0.0.5) ; extra == 'analyzer'
Requires-Dist: numpy (<2,>=1.16) ; extra == 'analyzer'
Requires-Dist: pandas (<2.0,>=1.1) ; extra == 'analyzer'
Requires-Dist: shap (==0.36.0) ; extra == 'analyzer'
Provides-Extra: cli
Requires-Dist: Click ; extra == 'cli'
Requires-Dist: docker ; extra == 'cli'
Requires-Dist: jsonschema ; extra == 'cli'
Requires-Dist: pyhcl ; extra == 'cli'
Provides-Extra: model-monitoring
Requires-Dist: boxkite (<0.1,>=0.0.5) ; extra == 'model-monitoring'
